setupEM/__init__.py
setupEM/__main__.py
setupEM/setupEM.py
setupEM/data/SG13G2_100um.xml
setupEM/data/SG13G2_200um.xml
setupEM/data/SG13G2_nosub.xml
setupem-0.1.22.dist-info/METADATA
setupem-0.1.22.dist-info/WHEEL
setupem-0.1.22.dist-info/entry_points.txt
setupem-0.1.22.dist-info/top_level.txt
setupem-0.1.22.dist-info/RECORD
