Metadata-Version: 2.4
Name: setupEM
Version: 0.1.22
Summary: Python tool for configuration of gds2palace workflow with GUI.
Author-email: Volker Muehlhaus <volker@muehlhaus.com>
Requires-Python: >=3.9
Requires-Dist: gds2palace>=0.1.16
Requires-Dist: PySide6
Requires-Dist: scipy
Requires-Dist: requests
Requires-Dist: scikit-rf
Requires-Dist: matplotlib
